restpf/__init__.py
restpf/main.py
restpf/metadata.py
restpf-0.0.1.dist-info/DESCRIPTION.rst
restpf-0.0.1.dist-info/METADATA
restpf-0.0.1.dist-info/RECORD
restpf-0.0.1.dist-info/WHEEL
restpf-0.0.1.dist-info/entry_points.txt
restpf-0.0.1.dist-info/metadata.json
restpf-0.0.1.dist-info/top_level.txt
